{"version":1,"resource":"vscode-remote://970-cs-2e13dc42-0d63-48dd-b125-09c0e5b14cc0.cs-asia-east1-cats.cloudshell.dev/home/yun777567/my-firebase-project/src/lib/firebase/db.ts","entries":[{"id":"fVA8.ts","timestamp":1738824376591},{"id":"qIPh.ts","timestamp":1738844553443},{"id":"XMuP.ts","timestamp":1738844689462},{"id":"5pcV.ts","timestamp":1738889784980},{"id":"XjkY.ts","source":"undoRedo.source","timestamp":1738889788631},{"id":"riKI.ts","timestamp":1738889798826},{"id":"1Q0z.ts","timestamp":1738889833121},{"id":"qzwj.ts","timestamp":1738889872970},{"id":"9Bi0.ts","timestamp":1738890014694},{"id":"ZRbL.ts","timestamp":1739160257540}]}